ptus/COMMIT_HASH.txt
ptus/VERSION.txt
ptus/__init__.py
ptus/constants.py
ptus/main.py
ptus/system.py
ptus/xcm.py
ptus/xcm_engine_rpc.py
ptus-0.1.2.dist-info/METADATA
ptus-0.1.2.dist-info/WHEEL
ptus-0.1.2.dist-info/entry_points.txt
ptus-0.1.2.dist-info/top_level.txt
ptus-0.1.2.dist-info/RECORD
